ccrdg/__init__.py
ccrdg/accel_gyro_data.py
ccrdg/battery_data.py
ccrdg/location_data.py
ccrdg-1.0.1.dist-info/METADATA
ccrdg-1.0.1.dist-info/WHEEL
ccrdg-1.0.1.dist-info/entry_points.txt
ccrdg-1.0.1.dist-info/top_level.txt
ccrdg-1.0.1.dist-info/RECORD
