Metadata-Version: 2.1
Name: ccrdg
Version: 1.0.1
Summary: Random data generator in cerebral cortex format
Home-page: https://github.com/MD2Korg/CerebralCortex-Random-Data-Generator
Author: MD2K.org
Author-email: dev@md2k.org
License: BSD2
Keywords: mHealth machine-learning data-analysis
Platform: UNKNOWN
Classifier: Development Status :: 5 - Production/Stable
Classifier: Intended Audience :: Healthcare Industry
Classifier: Intended Audience :: Science/Research
Classifier: License :: OSI Approved :: BSD License
Classifier: Natural Language :: English
Classifier: Programming Language :: Python :: 3
Classifier: Topic :: Scientific/Engineering :: Information Analysis
Classifier: Topic :: System :: Distributed Computing
Requires-Dist: cerebralcortex-kernel
